pynalyser/__init__.py
pynalyser/main.py
pynalyser/normalize_ast.py
pynalyser/portable_ast.py
pynalyser/py.typed
pynalyser/acr/__init__.py
pynalyser/acr/classes.py
pynalyser/acr/translation.py
pynalyser/acr/utils.py
pynalyser/analysis/__init__.py
pynalyser/analysis/_ref_types.py
pynalyser/analysis/_symb_types.py
pynalyser/analysis/_types.py
pynalyser/analysis/scope.py
pynalyser/analysis/symbols.py
pynalyser/analysis/tools.py
pynalyser/analysis/types.py
pynalyser-0.1.0.dist-info/LICENSE
pynalyser-0.1.0.dist-info/METADATA
pynalyser-0.1.0.dist-info/WHEEL
pynalyser-0.1.0.dist-info/top_level.txt
pynalyser-0.1.0.dist-info/RECORD
