Metadata-Version: 2.1
Name: pynalyser
Version: 0.1.0
Summary: Static Python Code Analyzer
Home-page: https://github.com/0dminnimda/pynalyser
Author: 0dminnimda
Author-email: 0dminnimda.contact@gmail.com
License: MIT
Project-URL: Bug tracker, https://github.com/0dminnimda/pynalyser/issues
Platform: UNKNOWN
Classifier: Development Status :: 2 - Pre-Alpha
Classifier: Intended Audience :: Developers
Classifier: License :: OSI Approved :: MIT License
Classifier: Programming Language :: Python
Classifier: Programming Language :: Python :: 3
Classifier: Programming Language :: Python :: 3 :: Only
Classifier: Programming Language :: Python :: 3.6
Classifier: Programming Language :: Python :: 3.7
Classifier: Programming Language :: Python :: 3.8
Classifier: Programming Language :: Python :: 3.9
Classifier: Topic :: Software Development :: Libraries :: Python Modules
Classifier: Topic :: Software Development :: Pre-processors
Classifier: Topic :: Utilities
Classifier: Typing :: Typed
Requires-Python: >=3.6
License-File: LICENSE
Requires-Dist: setuptools
Requires-Dist: attr
Provides-Extra: test
Requires-Dist: pytest ; extra == 'test'
Requires-Dist: pycodestyle ; extra == 'test'
Requires-Dist: mypy ; extra == 'test'
